<firma xmlns:xsi="http://www.w3.org/2001/XMLSchema-instance" xsi:noNamespaceSchemaLocation="zad4.xsd">
    <produkt id="aa">
        <nazwa>aa</nazwa>
        <producent>aa</producent>
        <cena>aa</cena>
    </produkt>
    <produkt id="aab">
        <nazwa>aa</nazwa>
        <producent>aaa</producent>
        <cena>aa</cena>
    </produkt>
    <zakup id_produkt="aa">
        <data_zakupu>a</data_zakupu>
        <ilosc>a</ilosc>
    </zakup>
    <zakup id_produkt="aab">
        <data_zakupu>a</data_zakupu>
        <ilosc>a</ilosc>
    </zakup>
</firma>